sws/__init__.py
sws/config.py
sws/simpleeval.py
sws_config-0.6.3.dist-info/METADATA
sws_config-0.6.3.dist-info/WHEEL
sws_config-0.6.3.dist-info/licenses/LICENSE
sws_config-0.6.3.dist-info/RECORD
