Metadata-Version: 2.4
Name: sws-config
Version: 0.6.3
Summary: Minimal pythonic config library for deep learning experiments
Project-URL: Homepage, https://github.com/lucasb-eyer/sws
Project-URL: Repository, https://github.com/lucasb-eyer/sws
Author: Lucas Beyer, OpenAI Assistant
License: MIT License
License-File: LICENSE
Keywords: cli,config,configuration,deep learning,experiments
Classifier: Development Status :: 3 - Alpha
Classifier: Intended Audience :: Developers
Classifier: License :: OSI Approved :: MIT License
Classifier: Operating System :: OS Independent
Classifier: Programming Language :: Python
Classifier: Programming Language :: Python :: 3
Classifier: Programming Language :: Python :: 3 :: Only
Classifier: Programming Language :: Python :: 3.9
Classifier: Programming Language :: Python :: 3.10
Classifier: Programming Language :: Python :: 3.11
Classifier: Programming Language :: Python :: 3.12
Classifier: Programming Language :: Python :: 3.13
Classifier: Topic :: Software Development :: Libraries
Requires-Python: >=3.9
Provides-Extra: test
Requires-Dist: pytest>=7; extra == 'test'
